snoopish_demo/__init__.py
snoopish_demo-0.0.1.dist-info/METADATA
snoopish_demo-0.0.1.dist-info/WHEEL
snoopish_demo-0.0.1.dist-info/top_level.txt
snoopish_demo-0.0.1.dist-info/RECORD
